Workbook

Sheet Leads
A1: # | B1: Priority | C1: Lead type | D1: Business | E1: Category | F1: Region | G1: DM on | H1: Instagram | I1: Facebook | J1: Phone | K1: Website | L1: What we found | M1: Suggested first DM (fill the [bracket] first) | N1: Check on Google Maps | O1: Status | P1: Assigned to | Q1: Date contacted | R1: Follow-up date | S1: Notes
A2: 1 | B2: HIGH | C2: No own website | D2: Ferny Way Bakery | E2: bakery | F2: Brisbane | G2: Facebook | I2: https://www.facebook.com/Ferny-Way-Bakery-689190028097407/ | J2: +61 7 3351 2708 | K2: https://www.facebook.com/Ferny-Way-Bakery-689190028097407/ | L2: no real website (uses www.facebook.com) | M2: Hi Ferny Way Bakery team! [one real detail from their page]. We're AceAds, a web design studio. We noticed that when people in Brisbane search for a bakery on Google, they only find your Facebook, not a website of your own. We'd be happy to make you a free preview of what a website could look like. Want one? No cost, no obligation. | N2: Open map | O2: Not contacted
A3: 2 | B3: HIGH | C3: No own website | D3: Karana Krusty Bakery | E3: bakery | F3: Brisbane | G3: Facebook | I3: https://www.facebook.com/Bakery-Karana-Downs-624286981023430/ | J3: +61 7 3201 0104 | K3: https://www.facebook.com/Bakery-Karana-Downs-624286981023430/ | L3: no real website (uses www.facebook.com) | M3: Hi Karana Krusty Bakery team! [one real detail from their page]. We're AceAds, a web design studio. We noticed that when people in Brisbane search for a bakery on Google, they only find your Facebook, not a website of your own. We'd be happy to make you a free preview of what a website could look like. Want one? No cost, no obligation. | N3: Open map | O3: Not contacted
A4: 3 | B4: HIGH | C4: No own website | D4: Flat Lizard Brewing | E4: bar or pub | F4: Brisbane | G4: Facebook | I4: https://www.facebook.com/flatlizardbrewing/ | K4: https://www.facebook.com/flatlizardbrewing/ | L4: no real website (uses www.facebook.com) | M4: Hi Flat Lizard Brewing team! [one real detail from their page]. We're AceAds, a web design studio. We noticed that when people in Brisbane search for a bar on Google, they only find your Facebook, not a website of your own. We'd be happy to make you a free preview of what a website could look like. Want one? No cost, no obligation. | N4: Open map | O4: Not contacted
A5: 4 | B5: HIGH | C5: No own website | D5: Bella Vision Hair Studio | E5: barber or hairdresser | F5: Brisbane | G5: Facebook | I5: https://www.facebook.com/bellavisionhairstudio132 | J5: +61 7 3351 0200 | K5: https://www.facebook.com/bellavisionhairstudio132/ | L5: no real website (uses www.facebook.com) | M5: Hi Bella Vision Hair Studio team! [one real detail from their page]. We're AceAds, a web design studio. We noticed that when people in Brisbane search for a hairdresser on Google, they only find your Facebook, not a website of your own. We'd be happy to make you a free preview of what a website could look like. Want one? No cost, no obligation. | N5: Open map | O5: Not contacted
A6: 5 | B6: HIGH | C6: No own website | D6: Brass Knuckles Barber | E6: barber or hairdresser | F6: Brisbane | G6: Instagram | H6: https://www.instagram.com/brassknuckles_barber/ | J6: +61 493 369 135 | K6: https://www.instagram.com/brassknuckles_barber/ | L6: no real website (uses www.instagram.com) | M6: Hi Brass Knuckles Barber team! [one real detail from their page]. We're AceAds, a web design studio. We noticed that when people in Brisbane search for a hairdresser on Google, they only find your Instagram, not a website of your own. We'd be happy to make you a free preview of what a website could look like. Want one? No cost, no obligation. | N6: Open map | O6: Not contacted
A7: 6 | B7: HIGH | C7: No own website | D7: Crown and Co Barbers | E7: barber or hairdresser | F7: Brisbane | G7: Facebook | I7: https://www.facebook.com/crownandcobarbers/?ref=page_internal | K7: https://www.facebook.com/crownandcobarbers/?ref=page_internal | L7: no real website (uses www.facebook.com) | M7: Hi Crown and Co Barbers team! [one real detail from their page]. We're AceAds, a web design studio. We noticed that when people in Brisbane search for a hairdresser on Google, they only find your Facebook, not a website of your own. We'd be happy to make you a free preview of what a website could look like. Want one? No cost, no obligation. | N7: Open map | O7: Not contacted
A8: 7 | B8: HIGH | C8: No own website | D8: Kin Barbershop | E8: barber or hairdresser | F8: Brisbane | G8: Facebook | I8: https://www.facebook.com/p/Kin-Barbershop-61557611918699 | J8: +61 411 614 614 | K8: https://kinbarbershop.square.site/ | L8: no real website (uses kinbarbershop.square.site) | M8: Hi Kin Barbershop team! [one real detail from their page]. We're AceAds, a web design studio. We noticed that when people in Brisbane search for a hairdresser on Google, they only find your Facebook, not a website of your own. We'd be happy to make you a free preview of what a website could look like. Want one? No cost, no obligation. | N8: Open map | O8: Not contacted
A9: 8 | B9: HIGH | C9: No own website | D9: Scotty Barberino's Barber Shop | E9: barber or hairdresser | F9: Brisbane | G9: Facebook | I9: https://facebook.com/scottybarberinos/ | J9: +61 7 3289 2468 | K9: https://facebook.com/scottybarberinos/ | L9: no real website (uses facebook.com) | M9: Hi Scotty Barberino's Barber Shop team! [one real detail from their page]. We're AceAds, a web design studio. We noticed that when people in Brisbane search for a hairdresser on Google, they only find your Facebook, not a website of your own. We'd be happy to make you a free preview of what a website could look like. Want one? No cost, no obligation. | N9: Open map | O9: Not contacted
A10: 9 | B10: HIGH | C10: No own website | D10: Terry Dobie Hairdressing | E10: barber or hairdresser | F10: Brisbane | G10: Facebook | I10: https://www.facebook.com/Terrydobiehair/ | K10: https://terrydobiehair.wixsite.com/mysite | L10: no real website (uses terrydobiehair.wixsite.com) | M10: Hi Terry Dobie Hairdressing team! [one real detail from their page]. We're AceAds, a web design studio. We noticed that when people in Brisbane search for a hairdresser on Google, they only find your Facebook, not a website of your own. We'd be happy to make you a free preview of what a website could look like. Want one? No cost, no obligation. | N10: Open map | O10: Not contacted
A11: 10 | B11: HIGH | C11: No own website | D11: Nail Today | E11: beauty salon | F11: Brisbane | G11: Facebook | I11: https://www.facebook.com/profile.php?id=100063881476277 | J11: +61 414 266 235 | K11: https://www.facebook.com/profile.php?id=100063881476277 | L11: no real website (uses www.facebook.com) | M11: Hi Nail Today team! [one real detail from their page]. We're AceAds, a web design studio. We noticed that when people in Brisbane search for a beauty salon on Google, they only find your Facebook, not a website of your own. We'd be happy to make you a free preview of what a website could look like. Want one? No cost, no obligation. | N11: Open map | O11: Not contacted
A12: 11 | B12: HIGH | C12: No own website | D12: Bancroft Roasters, Bardon | E12: cafe | F12: Brisbane | G12: Facebook | I12: https://m.facebook.com/story.php?story_fbid=2013500125499490&id=487145808134937&sfnsn=mo | K12: https://m.facebook.com/story.php?story_fbid=2013500125499490&id=487145808134937&sfnsn=mo | L12: no real website (uses m.facebook.com) | M12: Hi Bancroft Roasters, Bardon team! [one real detail from their page]. We're AceAds, a web design studio. We noticed that when people in Brisbane search for a cafe on Google, they only find your Facebook, not a website of your own. We'd be happy to make you a free preview of what a website could look like. Want one? No cost, no obligation. | N12: Open map | O12: Not contacted
A13: 12 | B13: HIGH | C13: No own website | D13: Bardon Thyme | E13: cafe | F13: Brisbane | G13: Instagram | H13: https://www.instagram.com/bardonthyme/?hl=en | J13: +61 433 022 991 | K13: https://www.instagram.com/bardonthyme/?hl=en | L13: no real website (uses www.instagram.com) | M13: Hi Bardon Thyme team! [one real detail from their page]. We're AceAds, a web design studio. We noticed that when people in Brisbane search for a cafe on Google, they only find your Instagram, not a website of your own. We'd be happy to make you a free preview of what a website could look like. Want one? No cost, no obligation. | N13: Open map | O13: Not contacted
A14: 13 | B14: HIGH | C14: No own website | D14: Canter & Colt | E14: cafe | F14: Brisbane | G14: Facebook | I14: https://www.facebook.com/canterandcolt | J14: +61 7 3289 1087 | K14: https://www.facebook.com/canterandcolt | L14: no real website (uses www.facebook.com) | M14: Hi Canter & Colt team! [one real detail from their page]. We're AceAds, a web design studio. We noticed that when people in Brisbane search for a cafe on Google, they only find your Facebook, not a website of your own. We'd be happy to make you a free preview of what a website could look like. Want one? No cost, no obligation. | N14: Open map | O14: Not contacted
A15: 14 | B15: HIGH | C15: No own website | D15: Coffee Warden | E15: cafe | F15: Brisbane | G15: Facebook | I15: https://www.facebook.com/Coffee-Warden-Sandgate-380818316058328/ | K15: https://www.facebook.com/Coffee-Warden-Sandgate-380818316058328/ | L15: no real website (uses www.facebook.com) | M15: Hi Coffee Warden team! [one real detail from their page]. We're AceAds, a web design studio. We noticed that when people in Brisbane search for a cafe on Google, they only find your Facebook, not a website of your own. We'd be happy to make you a free preview of what a website could look like. Want one? No cost, no obligation. | N15: Open map | O15: Not contacted
A16: 15 | B16: HIGH | C16: No own website | D16: Coffee on the Way | E16: cafe | F16: Brisbane | G16: Facebook | I16: https://www.facebook.com/people/Coffee-on-the-Way/100057414793271/ | J16: +61 407 900 595 | K16: https://www.facebook.com/people/Coffee-on-the-Way/100057414793271/ | L16: no real website (uses www.facebook.com) | M16: Hi Coffee on the Way team! [one real detail from their page]. We're AceAds, a web design studio. We noticed that when people in Brisbane search for a cafe on Google, they only find your Facebook, not a website of your own. We'd be happy to make you a free preview of what a website could look like. Want one? No cost, no obligation. | N16: Open map | O16: Not contacted
A17: 16 | B17: HIGH | C17: No own website | D17: Dropout Espresso | E17: cafe | F17: Brisbane | G17: Facebook | I17: https://www.facebook.com/Dropout-espresso-110045364260266/ | J17: +61 7 3289 5555 | K17: https://www.facebook.com/Dropout-espresso-110045364260266/ | L17: no real website (uses www.facebook.com) | M17: Hi Dropout Espresso team! [one real detail from their page]. We're AceAds, a web design studio. We noticed that when people in Brisbane search for a cafe on Google, they only find your Facebook, not a website of your own. We'd be happy to make you a free preview of what a website could look like. Want one? No cost, no obligation. | N17: Open map | O17: Not contacted
A18: 17 | B18: HIGH | C18: No own website | D18: Fraser's Newstead | E18: cafe | F18: Brisbane | G18: Instagram | H18: https://www.instagram.com/frasersnewstead/ | K18: https://www.instagram.com/frasersnewstead/ | L18: no real website (uses www.instagram.com) | M18: Hi Fraser's Newstead team! [one real detail from their page]. We're AceAds, a web design studio. We noticed that when people in Brisbane search for a cafe on Google, they only find your Instagram, not a website of your own. We'd be happy to make you a free preview of what a website could look like. Want one? No cost, no obligation. | N18: Open map | O18: Not contacted
A19: 18 | B19: HIGH | C19: No own website | D19: Graceville Moments Cafe | E19: cafe | F19: Brisbane | G19: Facebook | I19: https://www.facebook.com/gracevillemoments/ | J19: +61 402 680 192 | K19: https://www.facebook.com/gracevillemoments/ | L19: no real website (uses www.facebook.com) | M19: Hi Graceville Moments Cafe team! [one real detail from their page]. We're AceAds, a web design studio. We noticed that when people in Brisbane search for a cafe on Google, they only find your Facebook, not a website of your own. We'd be happy to make you a free preview of what a website could look like. Want one? No cost, no obligation. | N19: Open map | O19: Not contacted
A20: 19 | B20: HIGH | C20: No own website | D20: Little Red Providore | E20: cafe | F20: Brisbane | G20: Facebook | I20: https://www.facebook.com/littleredprovidore/ | J20: +61 7 3369 4044 | K20: https://www.facebook.com/littleredprovidore/ | L20: no real website (uses www.facebook.com) | M20: Hi Little Red Providore team! [one real detail from their page]. We're AceAds, a web design studio. We noticed that when people in Brisbane search for a cafe on Google, they only find your Facebook, not a website of your own. We'd be happy to make you a free preview of what a website could look like. Want one? No cost, no obligation. | N20: Open map | O20: Not contacted
A21: 20 | B21: HIGH | C21: No own website | D21: Paper Moon Coffee House and Functions | E21: cafe | F21: Brisbane | G21: Facebook | I21: https://www.facebook.com/profile.php?id=61584852192002 | J21: +61 408 135 812 | K21: https://www.facebook.com/profile.php?id=61584852192002 | L21: no real website (uses www.facebook.com) | M21: Hi Paper Moon Coffee House and Functions team! [one real detail from their page]. We're AceAds, a web design studio. We noticed that when people in Brisbane search for a cafe on Google, they only find your Facebook, not a website of your own. We'd be happy to make you a free preview of what a website could look like. Want one? No cost, no obligation. | N21: Open map | O21: Not contacted
A22: 21 | B22: HIGH | C22: No own website | D22: Proud To Serve | E22: cafe | F22: Brisbane | G22: Facebook | I22: https://www.facebook.com/people/PROUD-to-SERVE/100083122461252/ | J22: +61 433 790 454 | K22: https://www.facebook.com/people/PROUD-to-SERVE/100083122461252/ | L22: no real website (uses www.facebook.com) | M22: Hi Proud To Serve team! [one real detail from their page]. We're AceAds, a web design studio. We noticed that when people in Brisbane search for a cafe on Google, they only find your Facebook, not a website of your own. We'd be happy to make you a free preview of what a website could look like. Want one? No cost, no obligation. | N22: Open map | O22: Not contacted
A23: 22 | B23: HIGH | C23: No own website | D23: Remedy Espresso Cafe | E23: cafe | F23: Brisbane | G23: Facebook | I23: https://www.facebook.com/remedyec/ | J23: +61 7 3818 6687 | K23: https://www.facebook.com/remedyec/ | L23: no real website (uses www.facebook.com) | M23: Hi Remedy Espresso Cafe team! [one real detail from their page]. We're AceAds, a web design studio. We noticed that when people in Brisbane search for a cafe on Google, they only find your Facebook, not a website of your own. We'd be happy to make you a free preview of what a website could look like. Want one? No cost, no obligation. | N23: Open map | O23: Not contacted
A24: 23 | B24: HIGH | C24: No own website | D24: Rooka Acai | E24: cafe | F24: Brisbane | G24: Instagram | H24: https://www.instagram.com/rookaacai | J24: +61 435 383 803 | K24: https://www.instagram.com/rookaacai | L24: no real website (uses www.instagram.com) | M24: Hi Rooka Acai team! [one real detail from their page]. We're AceAds, a web design studio. We noticed that when people in Brisbane search for a cafe on Google, they only find your Instagram, not a website of your own. We'd be happy to make you a free preview of what a website could look like. Want one? No cost, no obligation. | N24: Open map | O24: Not contacted
A25: 24 | B25: HIGH | C25: No own website | D25: Story Behind The Coffee | E25: cafe | F25: Brisbane | G25: Facebook | I25: https://www.facebook.com/storybehindthecoffee/ | J25: +61 475 209 660 | K25: https://www.facebook.com/storybehindthecoffee/ | L25: no real website (uses www.facebook.com) | M25: Hi Story Behind The Coffee team! [one real detail from their page]. We're AceAds, a web design studio. We noticed that when people in Brisbane search for a cafe on Google, they only find your Facebook, not a website of your own. We'd be happy to make you a free preview of what a website could look like. Want one? No cost, no obligation. | N25: Open map | O25: Not contacted
A26: 25 | B26: HIGH | C26: No own website | D26: Sundays Cafe | E26: cafe | F26: Brisbane | G26: Facebook | I26: https://www.facebook.com/SundaysCoffeeHouseRocklea/ | J26: +61 7 3150 8771 | K26: https://www.facebook.com/SundaysCoffeeHouseRocklea/ | L26: no real website (uses www.facebook.com) | M26: Hi Sundays Cafe team! [one real detail from their page]. We're AceAds, a web design studio. We noticed that when people in Brisbane search for a cafe on Google, they only find your Facebook, not a website of your own. We'd be happy to make you a free preview of what a website could look like. Want one? No cost, no obligation. | N26: Open map | O26: Not contacted
A27: 26 | B27: HIGH | C27: No own website | D27: The Brass | E27: cafe | F27: Brisbane | G27: Facebook | I27: https://www.facebook.com/profile.php?id=100093799565639 | J27: +61 7 3113 3636 | K27: https://www.facebook.com/profile.php?id=100093799565639 | L27: no real website (uses www.facebook.com) | M27: Hi The Brass team! [one real detail from their page]. We're AceAds, a web design studio. We noticed that when people in Brisbane search for a cafe on Google, they only find your Facebook, not a website of your own. We'd be happy to make you a free preview of what a website could look like. Want one? No cost, no obligation. | N27: Open map | O27: Not contacted
A28: 27 | B28: HIGH | C28: No own website | D28: The Woolshed. | E28: cafe | F28: Brisbane | G28: Instagram | H28: https://www.instagram.com/woolshed.bne/ | K28: https://www.instagram.com/woolshed.bne/ | L28: no real website (uses www.instagram.com) | M28: Hi The Woolshed. team! [one real detail from their page]. We're AceAds, a web design studio. We noticed that when people in Brisbane search for a cafe on Google, they only find your Instagram, not a website of your own. We'd be happy to make you a free preview of what a website could look like. Want one? No cost, no obligation. | N28: Open map | O28: Not contacted
A29: 28 | B29: HIGH | C29: No own website | D29: Vinty Bean | E29: cafe | F29: Brisbane | G29: Instagram | H29: https://www.instagram.com/vintybean/ | K29: https://www.instagram.com/vintybean/ | L29: no real website (uses www.instagram.com) | M29: Hi Vinty Bean team! [one real detail from their page]. We're AceAds, a web design studio. We noticed that when people in Brisbane search for a cafe on Google, they only find your Instagram, not a website of your own. We'd be happy to make you a free preview of what a website could look like. Want one? No cost, no obligation. | N29: Open map | O29: Not contacted
A30: 29 | B30: HIGH | C30: No own website | D30: Lifecycle Garage & Bespoke | E30: car or bike shop | F30: Brisbane | G30: Facebook | I30: https://www.facebook.com/lifecyclebrisbane | J30: +61 7 3831 2611 | K30: https://www.facebook.com/lifecyclebrisbane | L30: no real website (uses www.facebook.com) | M30: Hi Lifecycle Garage & Bespoke team! [one real detail from their page]. We're AceAds, a web design studio. We noticed that when people in Brisbane search for a car or bike shop on Google, they only find your Facebook, not a website of your own. We'd be happy to make you a free preview of what a website could look like. Want one? No cost, no obligation. | N30: Open map | O30: Not contacted
A31: 30 | B31: HIGH | C31: No own website | D31: Dinmore Fruit Barn | E31: deli or specialty food | F31: Brisbane | G31: Facebook | I31: https://www.facebook.com/pages/Dinmore-Fruit-Barn/190399727707208 | J31: +61 7 3282 4221 | K31: https://www.facebook.com/pages/Dinmore-Fruit-Barn/190399727707208 | L31: no real website (uses www.facebook.com) | M31: Hi Dinmore Fruit Barn team! [one real detail from their page]. We're AceAds, a web design studio. We noticed that when people in Brisbane search for a local food store on Google, they only find your Facebook, not a website of your own. We'd be happy to make you a free preview of what a website could look like. Want one? No cost, no obligation. | N31: Open map | O31: Not contacted
A32: 31 | B32: HIGH | C32: No own website | D32: Kadison And Lealta | E32: florist | F32: Brisbane | G32: Facebook | I32: https://www.facebook.com/kadisonandlealta/ | J32: +61 431 454 413 | K32: https://www.facebook.com/kadisonandlealta/ | L32: no real website (uses www.facebook.com) | M32: Hi Kadison And Lealta team! [one real detail from their page]. We're AceAds, a web design studio. We noticed that when people in Brisbane search for a florist on Google, they only find your Facebook, not a website of your own. We'd be happy to make you a free preview of what a website could look like. Want one? No cost, no obligation. | N32: Open map | O32: Not contacted
A33: 32 | B33: HIGH | C33: No own website | D33: Cherished Creations | E33: gift or homewares | F33: Brisbane | G33: Facebook | I33: https://www.facebook.com/cherishedcreationshandmade/ | J33: +61 419 343 235 | K33: https://www.facebook.com/cherishedcreationshandmade/ | L33: no real website (uses www.facebook.com) | M33: Hi Cherished Creations team! [one real detail from their page]. We're AceAds, a web design studio. We noticed that when people in Brisbane search for a gift shop on Google, they only find your Facebook, not a website of your own. We'd be happy to make you a free preview of what a website could look like. Want one? No cost, no obligation. | N33: Open map | O33: Not contacted
A34: 33 | B34: HIGH | C34: No own website | D34: Makers on Main | E34: gift or homewares | F34: Brisbane | G34: Facebook | I34: https://www.facebook.com/Makers-On-Main-281063809243994/ | J34: +61 458 966 151 | K34: https://www.facebook.com/Makers-On-Main-281063809243994/ | L34: no real website (uses www.facebook.com) | M34: Hi Makers on Main team! [one real detail from their page]. We're AceAds, a web design studio. We noticed that when people in Brisbane search for a gift shop on Google, they only find your Facebook, not a website of your own. We'd be happy to make you a free preview of what a website could look like. Want one? No cost, no obligation. | N34: Open map | O34: Not contacted
A35: 34 | B35: HIGH | C35: No own website | D35: Petrie 2nd Hand Furniture | E35: gift or homewares | F35: Brisbane | G35: Facebook | I35: https://www.facebook.com/people/Petrie-secondhand-furniture/100057573274067/ | J35: +61 432 059 374 | K35: https://petrie-secondhand-furniture.business.site/ | L35: no real website (uses petrie-secondhand-furniture.business.site) | M35: Hi Petrie 2nd Hand Furniture team! [one real detail from their page]. We're AceAds, a web design studio. We noticed that when people in Brisbane search for a gift shop on Google, they only find your Facebook, not a website of your own. We'd be happy to make you a free preview of what a website could look like. Want one? No cost, no obligation. | N35: Open map | O35: Not contacted
A36: 35 | B36: HIGH | C36: No own website | D36: Shady Dayz Gifts & Homewares | E36: gift or homewares | F36: Brisbane | G36: Facebook | I36: https://www.facebook.com/shadydayzgifts/ | J36: +61 7 3289 1833 | K36: https://www.facebook.com/shadydayzgifts/ | L36: no real website (uses www.facebook.com) | M36: Hi Shady Dayz Gifts & Homewares team! [one real detail from their page]. We're AceAds, a web design studio. We noticed that when people in Brisbane search for a gift shop on Google, they only find your Facebook, not a website of your own. We'd be happy to make you a free preview of what a website could look like. Want one? No cost, no obligation. | N36: Open map | O36: Not contacted
A37: 36 | B37: HIGH | C37: No own website | D37: Canary Lane | E37: jeweller | F37: Brisbane | G37: Facebook | I37: https://www.facebook.com/Canary-Lane-686290855153091/ | J37: +61 7 3852 2997 | K37: https://www.facebook.com/Canary-Lane-686290855153091/ | L37: no real website (uses www.facebook.com) | M37: Hi Canary Lane team! [one real detail from their page]. We're AceAds, a web design studio. We noticed that when people in Brisbane search for a jeweller on Google, they only find your Facebook, not a website of your own. We'd be happy to make you a free preview of what a website could look like. Want one? No cost, no obligation. | N37: Open map | O37: Not contacted
A38: 37 | B38: HIGH | C38: No own website | D38: Ascot Automotive | E38: mechanic | F38: Brisbane | G38: Facebook | I38: https://www.facebook.com/ascotautomotive4007/ | J38: +61 7 3262 2433 | K38: https://www.facebook.com/ascotautomotive4007/ | L38: no real website (uses www.facebook.com) | M38: Hi Ascot Automotive team! [one real detail from their page]. We're AceAds, a web design studio. We noticed that when people in Brisbane search for a mechanic on Google, they only find your Facebook, not a website of your own. We'd be happy to make you a free preview of what a website could look like. Want one? No cost, no obligation. | N38: Open map | O38: Not contacted
A39: 38 | B39: HIGH | C39: No own website | D39: Next Up Performance & Dyno Tuning | E39: mechanic | F39: Brisbane | G39: Facebook | I39: https://www.facebook.com/next.up.5/ | K39: https://www.facebook.com/next.up.5/ | L39: no real website (uses www.facebook.com) | M39: Hi Next Up Performance & Dyno Tuning team! [one real detail from their page]. We're AceAds, a web design studio. We noticed that when people in Brisbane search for a mechanic on Google, they only find your Facebook, not a website of your own. We'd be happy to make you a free preview of what a website could look like. Want one? No cost, no obligation. | N39: Open map | O39: Not contacted
A40: 39 | B40: HIGH | C40: No own website | D40: Prince Auto & Tyre Service | E40: mechanic | F40: Brisbane | G40: Facebook | I40: https://www.facebook.com/princeauto111/ | J40: +61 402 779 568 | K40: https://www.facebook.com/princeauto111/ | L40: no real website (uses www.facebook.com) | M40: Hi Prince Auto & Tyre Service team! [one real detail from their page]. We're AceAds, a web design studio. We noticed that when people in Brisbane search for a mechanic on Google, they only find your Facebook, not a website of your own. We'd be happy to make you a free preview of what a website could look like. Want one? No cost, no obligation. | N40: Open map | O40: Not contacted
A41: 40 | B41: HIGH | C41: No own website | D41: Shear Designz | E41: pet business | F41: Brisbane | G41: Facebook | I41: https://www.facebook.com/caninestylist.com.au/ | J41: +61 7 3889 0333 | K41: https://www.facebook.com/caninestylist.com.au/ | L41: no real website (uses www.facebook.com) | M41: Hi Shear Designz team! [one real detail from their page]. We're AceAds, a web design studio. We noticed that when people in Brisbane search for a pet shop on Google, they only find your Facebook, not a website of your own. We'd be happy to make you a free preview of what a website could look like. Want one? No cost, no obligation. | N41: Open map | O41: Not contacted
A42: 41 | B42: HIGH | C42: No own website | D42: Block House Coffe | E42: restaurant | F42: Brisbane | G42: Facebook | I42: https://www.facebook.com/Blockhouseeatdrink/ | J42: +61 7 3172 6869 | K42: https://www.facebook.com/Blockhouseeatdrink/ | L42: no real website (uses www.facebook.com) | M42: Hi Block House Coffe team! [one real detail from their page]. We're AceAds, a web design studio. We noticed that when people in Brisbane search for a restaurant on Google, they only find your Facebook, not a website of your own. We'd be happy to make you a free preview of what a website could look like. Want one? No cost, no obligation. | N42: Open map | O42: Not contacted
A43: 42 | B43: HIGH | C43: No own website | D43: Caxton Street Brewing Co | E43: restaurant | F43: Brisbane | G43: Instagram | H43: https://www.instagram.com/caxtonstreetbrewing/?hl=en | K43: https://www.instagram.com/caxtonstreetbrewing/?hl=en | L43: no real website (uses www.instagram.com) | M43: Hi Caxton Street Brewing Co team! [one real detail from their page]. We're AceAds, a web design studio. We noticed that when people in Brisbane search for a restaurant on Google, they only find your Instagram, not a website of your own. We'd be happy to make you a free preview of what a website could look like. Want one? No cost, no obligation. | N43: Open map | O43: Not contacted
A44: 43 | B44: HIGH | C44: No own website | D44: Graceville Pizza | E44: restaurant | F44: Brisbane | G44: Facebook | I44: https://www.facebook.com/GracevillePizza/ | J44: +61 7 3568 6888 | K44: https://www.facebook.com/GracevillePizza/ | L44: no real website (uses www.facebook.com) | M44: Hi Graceville Pizza team! [one real detail from their page]. We're AceAds, a web design studio. We noticed that when people in Brisbane search for a restaurant on Google, they only find your Facebook, not a website of your own. We'd be happy to make you a free preview of what a website could look like. Want one? No cost, no obligation. | N44: Open map | O44: Not contacted
A45: 44 | B45: HIGH | C45: No own website | D45: Momiji | E45: restaurant | F45: Brisbane | G45: Facebook | I45: https://www.facebook.com/MomijiJapaneseRestaurant/ | J45: +61 425 620 360 | K45: https://www.facebook.com/MomijiJapaneseRestaurant/ | L45: no real website (uses www.facebook.com) | M45: Hi Momiji team! [one real detail from their page]. We're AceAds, a web design studio. We noticed that when people in Brisbane search for a restaurant on Google, they only find your Facebook, not a website of your own. We'd be happy to make you a free preview of what a website could look like. Want one? No cost, no obligation. | N45: Open map | O45: Not contacted
A46: 45 | B46: HIGH | C46: No own website | D46: Pimnipa Thai Kitchen | E46: restaurant | F46: Brisbane | G46: Facebook | I46: https://m.facebook.com/61579010138892/ | J46: +61 422 906 464 | K46: https://m.facebook.com/61579010138892/ | L46: no real website (uses m.facebook.com) | M46: Hi Pimnipa Thai Kitchen team! [one real detail from their page]. We're AceAds, a web design studio. We noticed that when people in Brisbane search for a restaurant on Google, they only find your Facebook, not a website of your own. We'd be happy to make you a free preview of what a website could look like. Want one? No cost, no obligation. | N46: Open map | O46: Not contacted
A47: 46 | B47: HIGH | C47: No own website | D47: Sushi Gruhi | E47: restaurant | F47: Brisbane | G47: Facebook | I47: https://www.facebook.com/sushiaruhi/ | K47: https://www.facebook.com/sushiaruhi/ | L47: no real website (uses www.facebook.com) | M47: Hi Sushi Gruhi team! [one real detail from their page]. We're AceAds, a web design studio. We noticed that when people in Brisbane search for a restaurant on Google, they only find your Facebook, not a website of your own. We'd be happy to make you a free preview of what a website could look like. Want one? No cost, no obligation. | N47: Open map | O47: Not contacted
A48: 47 | B48: HIGH | C48: No own website | D48: G-Free Donuts | E48: takeaway | F48: Brisbane | G48: Instagram | H48: https://www.instagram.com/gfreedonuts.uq | J48: +61 404 599 213 | K48: https://www.instagram.com/gfreedonuts.uq | L48: no real website (uses www.instagram.com) | M48: Hi G-Free Donuts team! [one real detail from their page]. We're AceAds, a web design studio. We noticed that when people in Brisbane search for a takeaway on Google, they only find your Instagram, not a website of your own. We'd be happy to make you a free preview of what a website could look like. Want one? No cost, no obligation. | N48: Open map | O48: Not contacted
A49: 48 | B49: HIGH | C49: No own website | D49: Kebab & Charcoal Place | E49: takeaway | F49: Brisbane | G49: Facebook | I49: https://www.facebook.com/kebabncharcoalplace | J49: +61 7 3607 1058 | K49: https://www.facebook.com/kebabncharcoalplace | L49: no real website (uses www.facebook.com) | M49: Hi Kebab & Charcoal Place team! [one real detail from their page]. We're AceAds, a web design studio. We noticed that when people in Brisbane search for a takeaway on Google, they only find your Facebook, not a website of your own. We'd be happy to make you a free preview of what a website could look like. Want one? No cost, no obligation. | N49: Open map | O49: Not contacted
A50: 49 | B50: HIGH | C50: No own website | D50: Red Dolphin Seafoods | E50: takeaway | F50: Brisbane | G50: Facebook | I50: https://www.facebook.com/profile.php?id=100071592963125 | J50: +61 7 3284 8703 | K50: https://www.facebook.com/profile.php?id=100071592963125 | L50: no real website (uses www.facebook.com) | M50: Hi Red Dolphin Seafoods team! [one real detail from their page]. We're AceAds, a web design studio. We noticed that when people in Brisbane search for a takeaway on Google, they only find your Facebook, not a website of your own. We'd be happy to make you a free preview of what a website could look like. Want one? No cost, no obligation. | N50: Open map | O50: Not contacted
A51: 50 | B51: HIGH | C51: No own website | D51: Yabby Road | E51: takeaway | F51: Brisbane | G51: Facebook | I51: https://www.facebook.com/yabbeyroad/ | J51: +61 499 922 239 | K51: https://www.facebook.com/yabbeyroad/ | L51: no real website (uses www.facebook.com) | M51: Hi Yabby Road team! [one real detail from their page]. We're AceAds, a web design studio. We noticed that when people in Brisbane search for a takeaway on Google, they only find your Facebook, not a website of your own. We'd be happy to make you a free preview of what a website could look like. Want one? No cost, no obligation. | N51: Open map | O51: Not contacted
A52: 51 | B52: HIGH | C52: No own website | D52: Mister Cuts Barber Shop | E52: barber or hairdresser | F52: Cairns | G52: Facebook | I52: https://www.facebook.com/mistercutsbarbershopcairns | K52: https://www.facebook.com/mistercutsbarbershopcairns | L52: no real website (uses www.facebook.com) | M52: Hi Mister Cuts Barber Shop team! [one real detail from their page]. We're AceAds, a web design studio. We noticed that when people in Cairns search for a hairdresser on Google, they only find your Facebook, not a website of your own. We'd be happy to make you a free preview of what a website could look like. Want one? No cost, no obligation. | N52: Open map | O52: Not contacted
A53: 52 | B53: HIGH | C53: No own website | D53: Mrs Delicious | E53: cafe | F53: Cairns | G53: Facebook | I53: https://www.facebook.com/photo/?fbid=122113102580862715&set=a.122095944620862715 | K53: https://www.facebook.com/photo/?fbid=122113102580862715&set=a.122095944620862715 | L53: no real website (uses www.facebook.com) | M53: Hi Mrs Delicious team! [one real detail from their page]. We're AceAds, a web design studio. We noticed that when people in Cairns search for a cafe on Google, they only find your Facebook, not a website of your own. We'd be happy to make you a free preview of what a website could look like. Want one? No cost, no obligation. | N53: Open map | O53: Not contacted
A54: 53 | B54: HIGH | C54: No own website | D54: BBQ Brothers | E54: restaurant | F54: Cairns | G54: Facebook | I54: https://www.facebook.com/bbqbrothersaustralia | K54: https://www.facebook.com/bbqbrothersaustralia | L54: no real website (uses www.facebook.com) | M54: Hi BBQ Brothers team! [one real detail from their page]. We're AceAds, a web design studio. We noticed that when people in Cairns search for a restaurant on Google, they only find your Facebook, not a website of your own. We'd be happy to make you a free preview of what a website could look like. Want one? No cost, no obligation. | N54: Open map | O54: Not contacted
A55: 54 | B55: HIGH | C55: No own website | D55: Ganbaranba | E55: restaurant | F55: Cairns | G55: Instagram | H55: https://www.instagram.com/cool_ganba | K55: https://www.instagram.com/cool_ganba/ | L55: no real website (uses www.instagram.com) | M55: Hi Ganbaranba team! [one real detail from their page]. We're AceAds, a web design studio. We noticed that when people in Cairns search for a restaurant on Google, they only find your Instagram, not a website of your own. We'd be happy to make you a free preview of what a website could look like. Want one? No cost, no obligation. | N55: Open map | O55: Not contacted
A56: 55 | B56: HIGH | C56: No own website | D56: Sushi Roll King | E56: restaurant | F56: Cairns | G56: Facebook | I56: https://www.facebook.com/Sushi-Rollking-Sheridan-869079169913894/?notify_field=hours&modal=profile_completion | J56: +61 490 251 556 | K56: https://www.facebook.com/Sushi-Rollking-Sheridan-869079169913894/?notify_field=hours&modal=profile_completion | L56: no real website (uses www.facebook.com) | M56: Hi Sushi Roll King team! [one real detail from their page]. We're AceAds, a web design studio. We noticed that when people in Cairns search for a restaurant on Google, they only find your Facebook, not a website of your own. We'd be happy to make you a free preview of what a website could look like. Want one? No cost, no obligation. | N56: Open map | O56: Not contacted
A57: 56 | B57: HIGH | C57: No own website | D57: Art Taste Cafe | E57: bakery | F57: Gold Coast | G57: Facebook | I57: https://www.facebook.com/Arttastecaferobina/ | J57: +61 7 5580 8609 | K57: https://www.facebook.com/Arttastecaferobina/ | L57: no real website (uses www.facebook.com) | M57: Hi Art Taste Cafe team! [one real detail from their page]. We're AceAds, a web design studio. We noticed that when people in Gold Coast search for a bakery on Google, they only find your Facebook, not a website of your own. We'd be happy to make you a free preview of what a website could look like. Want one? No cost, no obligation. | N57: Open map | O57: Not contacted
A58: 57 | B58: HIGH | C58: No own website | D58: Kirra Beach Bakery | E58: bakery | F58: Gold Coast | G58: Facebook | I58: https://www.facebook.com/kirrabeachbakery/ | J58: +61 7 5536 5358 | K58: https://www.facebook.com/kirrabeachbakery/ | L58: no real website (uses www.facebook.com) | M58: Hi Kirra Beach Bakery team! [one real detail from their page]. We're AceAds, a web design studio. We noticed that when people in Gold Coast search for a bakery on Google, they only find your Facebook, not a website of your own. We'd be happy to make you a free preview of what a website could look like. Want one? No cost, no obligation. | N58: Open map | O58: Not contacted
A59: 58 | B59: HIGH | C59: No own website | D59: Pie Pie | E59: bakery | F59: Gold Coast | G59: Facebook | I59: https://www.facebook.com/piepieburleigh | J59: +61 7 3103 3503 | K59: https://www.facebook.com/piepieburleigh | L59: no real website (uses www.facebook.com) | M59: Hi Pie Pie team! [one real detail from their page]. We're AceAds, a web design studio. We noticed that when people in Gold Coast search for a bakery on Google, they only find your Facebook, not a website of your own. We'd be happy to make you a free preview of what a website could look like. Want one? No cost, no obligation. | N59: Open map | O59: Not contacted
A60: 59 | B60: HIGH | C60: No own website | D60: BarberLife | E60: barber or hairdresser | F60: Gold Coast | G60: Facebook | I60: https://www.facebook.com/varsity4227/ | J60: +61 423 663 425 | K60: https://www.facebook.com/varsity4227/ | L60: no real website (uses www.facebook.com) | M60: Hi BarberLife team! [one real detail from their page]. We're AceAds, a web design studio. We noticed that when people in Gold Coast search for a hairdresser on Google, they only find your Facebook, not a website of your own. We'd be happy to make you a free preview of what a website could look like. Want one? No cost, no obligation. | N60: Open map | O60: Not contacted
A61: 60 | B61: HIGH | C61: No own website | D61: DMH Palm Beach | E61: barber or hairdresser | F61: Gold Coast | G61: Facebook | I61: https://www.facebook.com/DMHPalmBeach/ | J61: +61 405 801 224 | K61: https://www.facebook.com/DMHPalmBeach/ | L61: no real website (uses www.facebook.com) | M61: Hi DMH Palm Beach team! [one real detail from their page]. We're AceAds, a web design studio. We noticed that when people in Gold Coast search for a hairdresser on Google, they only find your Facebook, not a website of your own. We'd be happy to make you a free preview of what a website could look like. Want one? No cost, no obligation. | N61: Open map | O61: Not contacted
A62: 61 | B62: HIGH | C62: No own website | D62: First Wave Hair | E62: barber or hairdresser | F62: Gold Coast | G62: Facebook | I62: https://www.facebook.com/Firstwave-Hair-Salon-Tugun-1473721922922601/ | J62: +61 7 5534 3036 | K62: https://www.facebook.com/Firstwave-Hair-Salon-Tugun-1473721922922601/ | L62: no real website (uses www.facebook.com) | M62: Hi First Wave Hair team! [one real detail from their page]. We're AceAds, a web design studio. We noticed that when people in Gold Coast search for a hairdresser on Google, they only find your Facebook, not a website of your own. We'd be happy to make you a free preview of what a website could look like. Want one? No cost, no obligation. | N62: Open map | O62: Not contacted
A63: 62 | B63: HIGH | C63: No own website | D63: Vanity Beauty Services | E63: beauty salon | F63: Gold Coast | G63: Facebook | I63: https://www.facebook.com/vanitybeautyservices/ | J63: +61 422 226 410 | K63: https://www.facebook.com/vanitybeautyservices/ | L63: no real website (uses www.facebook.com) | M63: Hi Vanity Beauty Services team! [one real detail from their page]. We're AceAds, a web design studio. We noticed that when people in Gold Coast search for a beauty salon on Google, they only find your Facebook, not a website of your own. We'd be happy to make you a free preview of what a website could look like. Want one? No cost, no obligation. | N63: Open map | O63: Not contacted
A64: 63 | B64: HIGH | C64: No own website | D64: Sea Wish | E64: boutique | F64: Gold Coast | G64: Facebook | I64: https://m.facebook.com/SeaWishShop/ | J64: +61 7 5536 3888 | K64: https://m.facebook.com/SeaWishShop/ | L64: no real website (uses m.facebook.com) | M64: Hi Sea Wish team! [one real detail from their page]. We're AceAds, a web design studio. We noticed that when people in Gold Coast search for a boutique on Google, they only find your Facebook, not a website of your own. We'd be happy to make you a free preview of what a website could look like. Want one? No cost, no obligation. | N64: Open map | O64: Not contacted
A65: 64 | B65: HIGH | C65: No own website | D65: Burleigh Beach Kiosk | E65: cafe | F65: Gold Coast | G65: Facebook | I65: https://www.facebook.com/burleighbeachkiosk | J65: +61 7 5520 2972 | K65: https://www.facebook.com/burleighbeachkiosk | L65: no real website (uses www.facebook.com) | M65: Hi Burleigh Beach Kiosk team! [one real detail from their page]. We're AceAds, a web design studio. We noticed that when people in Gold Coast search for a cafe on Google, they only find your Facebook, not a website of your own. We'd be happy to make you a free preview of what a website could look like. Want one? No cost, no obligation. | N65: Open map | O65: Not contacted
A66: 65 | B66: HIGH | C66: No own website | D66: Cafe 1291 | E66: cafe | F66: Gold Coast | G66: Facebook | I66: https://www.facebook.com/Cafetwelve91/ | J66: +61 427 883 742 | K66: https://www.facebook.com/Cafetwelve91/ | L66: no real website (uses www.facebook.com) | M66: Hi Cafe 1291 team! [one real detail from their page]. We're AceAds, a web design studio. We noticed that when people in Gold Coast search for a cafe on Google, they only find your Facebook, not a website of your own. We'd be happy to make you a free preview of what a website could look like. Want one? No cost, no obligation. | N66: Open map | O66: Not contacted
A67: 66 | B67: HIGH | C67: No own website | D67: Cafe Kirra | E67: cafe | F67: Gold Coast | G67: Facebook | I67: https://www.facebook.com/cafekirra/ | J67: +61 7 5536 2614 | K67: https://www.facebook.com/cafekirra/ | L67: no real website (uses www.facebook.com) | M67: Hi Cafe Kirra team! [one real detail from their page]. We're AceAds, a web design studio. We noticed that when people in Gold Coast search for a cafe on Google, they only find your Facebook, not a website of your own. We'd be happy to make you a free preview of what a website could look like. Want one? No cost, no obligation. | N67: Open map | O67: Not contacted
A68: 67 | B68: HIGH | C68: No own website | D68: Elephant Grounds Cafe | E68: cafe | F68: Gold Coast | G68: Facebook | I68: https://www.facebook.com/Elephant-Grounds-552246915107742/ | J68: +61 419 782 640 | K68: https://www.facebook.com/Elephant-Grounds-552246915107742/ | L68: no real website (uses www.facebook.com) | M68: Hi Elephant Grounds Cafe team! [one real detail from their page]. We're AceAds, a web design studio. We noticed that when people in Gold Coast search for a cafe on Google, they only find your Facebook, not a website of your own. We'd be happy to make you a free preview of what a website could look like. Want one? No cost, no obligation. | N68: Open map | O68: Not contacted
A69: 68 | B69: HIGH | C69: No own website | D69: Good Day Coffee | E69: cafe | F69: Gold Coast | G69: Instagram | H69: https://www.instagram.com/gooddaycoffee/?hl=en | K69: https://www.instagram.com/gooddaycoffee/?hl=en | L69: no real website (uses www.instagram.com) | M69: Hi Good Day Coffee team! [one real detail from their page]. We're AceAds, a web design studio. We noticed that when people in Gold Coast search for a cafe on Google, they only find your Instagram, not a website of your own. We'd be happy to make you a free preview of what a website could look like. Want one? No cost, no obligation. | N69: Open map | O69: Not contacted
A70: 69 | B70: HIGH | C70: No own website | D70: Los Vegos | E70: cafe | F70: Gold Coast | G70: Facebook | I70: https://www.facebook.com/Los-Vegos-Coolangatta-853780404959832/ | J70: +61 7 5599 3560 | K70: https://www.facebook.com/Los-Vegos-Coolangatta-853780404959832/ | L70: no real website (uses www.facebook.com) | M70: Hi Los Vegos team! [one real detail from their page]. We're AceAds, a web design studio. We noticed that when people in Gold Coast search for a cafe on Google, they only find your Facebook, not a website of your own. We'd be happy to make you a free preview of what a website could look like. Want one? No cost, no obligation. | N70: Open map | O70: Not contacted
A71: 70 | B71: HIGH | C71: No own website | D71: Mokacino's Cafe | E71: cafe | F71: Gold Coast | G71: Facebook | I71: https://www.facebook.com/Mokacinos/ | J71: +61 401 993 633 | K71: https://www.facebook.com/Mokacinos/ | L71: no real website (uses www.facebook.com) | M71: Hi Mokacino's Cafe team! [one real detail from their page]. We're AceAds, a web design studio. We noticed that when people in Gold Coast search for a cafe on Google, they only find your Facebook, not a website of your own. We'd be happy to make you a free preview of what a website could look like. Want one? No cost, no obligation. | N71: Open map | O71: Not contacted
A72: 71 | B72: HIGH | C72: No own website | D72: Old Paris Cafe | E72: cafe | F72: Gold Coast | G72: Facebook | I72: https://www.facebook.com/oldparisvarsity/ | J72: +61 7 5636 7477 | K72: https://www.facebook.com/oldparisvarsity/ | L72: no real website (uses www.facebook.com) | M72: Hi Old Paris Cafe team! [one real detail from their page]. We're AceAds, a web design studio. We noticed that when people in Gold Coast search for a cafe on Google, they only find your Facebook, not a website of your own. We'd be happy to make you a free preview of what a website could look like. Want one? No cost, no obligation. | N72: Open map | O72: Not contacted
A73: 72 | B73: HIGH | C73: No own website | D73: Seaway Kiosk | E73: cafe | F73: Gold Coast | G73: Facebook | I73: https://www.facebook.com/seawaykioskandjetty/ | J73: +61 7 5591 6970 | K73: https://www.facebook.com/seawaykioskandjetty/ | L73: no real website (uses www.facebook.com) | M73: Hi Seaway Kiosk team! [one real detail from their page]. We're AceAds, a web design studio. We noticed that when people in Gold Coast search for a cafe on Google, they only find your Facebook, not a website of your own. We'd be happy to make you a free preview of what a website could look like. Want one? No cost, no obligation. | N73: Open map | O73: Not contacted
A74: 73 | B74: HIGH | C74: No own website | D74: Sisterhood Coffee | E74: cafe | F74: Gold Coast | G74: Facebook | I74: https://www.facebook.com/Sisterhood-Coffee-2763461207004085/ | K74: https://www.facebook.com/Sisterhood-Coffee-2763461207004085/ | L74: no real website (uses www.facebook.com) | M74: Hi Sisterhood Coffee team! [one real detail from their page]. We're AceAds, a web design studio. We noticed that when people in Gold Coast search for a cafe on Google, they only find your Facebook, not a website of your own. We'd be happy to make you a free preview of what a website could look like. Want one? No cost, no obligation. | N74: Open map | O74: Not contacted
A75: 74 | B75: HIGH | C75: No own website | D75: The Lott Cafe | E75: cafe | F75: Gold Coast | G75: Facebook | I75: https://www.facebook.com/The-Lott-Cafe-Robina-1803600919948866/ | J75: +61 7 5593 0388 | K75: https://www.facebook.com/The-Lott-Cafe-Robina-1803600919948866/ | L75: no real website (uses www.facebook.com) | M75: Hi The Lott Cafe team! [one real detail from their page]. We're AceAds, a web design studio. We noticed that when people in Gold Coast search for a cafe on Google, they only find your Facebook, not a website of your own. We'd be happy to make you a free preview of what a website could look like. Want one? No cost, no obligation. | N75: Open map | O75: Not contacted
A76: 75 | B76: HIGH | C76: No own website | D76: West Brew Coffee | E76: cafe | F76: Gold Coast | G76: Facebook | I76: https://www.facebook.com/West-Brew-Coffee-106717397834618/ | J76: +61 437 541 888 | K76: https://www.facebook.com/West-Brew-Coffee-106717397834618/ | L76: no real website (uses www.facebook.com) | M76: Hi West Brew Coffee team! [one real detail from their page]. We're AceAds, a web design studio. We noticed that when people in Gold Coast search for a cafe on Google, they only find your Facebook, not a website of your own. We'd be happy to make you a free preview of what a website could look like. Want one? No cost, no obligation. | N76: Open map | O76: Not contacted
A77: 76 | B77: HIGH | C77: No own website | D77: Tugun Veterinary Surgery | E77: pet business | F77: Gold Coast | G77: Facebook | I77: https://www.facebook.com/TugunVets/ | J77: +61 7 5534 1928 | K77: https://www.facebook.com/TugunVets/ | L77: no real website (uses www.facebook.com) | M77: Hi Tugun Veterinary Surgery team! [one real detail from their page]. We're AceAds, a web design studio. We noticed that when people in Gold Coast search for a pet shop on Google, they only find your Facebook, not a website of your own. We'd be happy to make you a free preview of what a website could look like. Want one? No cost, no obligation. | N77: Open map | O77: Not contacted
A78: 77 | B78: HIGH | C78: No own website | D78: Big Chief | E78: takeaway | F78: Gold Coast | G78: Facebook | I78: https://www.facebook.com/Big-Chief-Burgers-Coolangatta-182275748504697/ | J78: +61 7 5536 1088 | K78: https://www.facebook.com/Big-Chief-Burgers-Coolangatta-182275748504697/ | L78: no real website (uses www.facebook.com) | M78: Hi Big Chief team! [one real detail from their page]. We're AceAds, a web design studio. We noticed that when people in Gold Coast search for a takeaway on Google, they only find your Facebook, not a website of your own. We'd be happy to make you a free preview of what a website could look like. Want one? No cost, no obligation. | N78: Open map | O78: Not contacted
A79: 78 | B79: HIGH | C79: No own website | D79: Flying Chicken | E79: takeaway | F79: Gold Coast | G79: Facebook | I79: https://www.facebook.com/pages/Flying-Chicken/2115204535392038 | J79: +61 7 5661 0848 | K79: https://www.facebook.com/pages/Flying-Chicken/2115204535392038 | L79: no real website (uses www.facebook.com) | M79: Hi Flying Chicken team! [one real detail from their page]. We're AceAds, a web design studio. We noticed that when people in Gold Coast search for a takeaway on Google, they only find your Facebook, not a website of your own. We'd be happy to make you a free preview of what a website could look like. Want one? No cost, no obligation. | N79: Open map | O79: Not contacted
A80: 79 | B80: HIGH | C80: No own website | D80: JJ's on Golden Four | E80: takeaway | F80: Gold Coast | G80: Facebook | I80: https://www.facebook.com/jjsongoldenfour/ | J80: +61 7 5534 1007 | K80: https://www.facebook.com/jjsongoldenfour/ | L80: no real website (uses www.facebook.com) | M80: Hi JJ's on Golden Four team! [one real detail from their page]. We're AceAds, a web design studio. We noticed that when people in Gold Coast search for a takeaway on Google, they only find your Facebook, not a website of your own. We'd be happy to make you a free preview of what a website could look like. Want one? No cost, no obligation. | N80: Open map | O80: Not contacted
A81: 80 | B81: HIGH | C81: No own website | D81: Bottletree Hotel Glamorgan Vale | E81: bar or pub | F81: Ipswich | G81: Facebook | I81: https://www.facebook.com/bottletreepub/ | K81: https://www.facebook.com/bottletreepub/ | L81: no real website (uses www.facebook.com) | M81: Hi Bottletree Hotel Glamorgan Vale team! [one real detail from their page]. We're AceAds, a web design studio. We noticed that when people in Ipswich search for a bar on Google, they only find your Facebook, not a website of your own. We'd be happy to make you a free preview of what a website could look like. Want one? No cost, no obligation. | N81: Open map | O81: Not contacted
A82: 81 | B82: HIGH | C82: No own website | D82: Loui's Fruit Market | E82: deli or specialty food | F82: Ipswich | G82: Facebook | I82: https://www.facebook.com/louisboovalfruitmarket/ | J82: +61 7 3202 1544 | K82: https://www.facebook.com/louisboovalfruitmarket/ | L82: no real website (uses www.facebook.com) | M82: Hi Loui's Fruit Market team! [one real detail from their page]. We're AceAds, a web design studio. We noticed that when people in Ipswich search for a local food store on Google, they only find your Facebook, not a website of your own. We'd be happy to make you a free preview of what a website could look like. Want one? No cost, no obligation. | N82: Open map | O82: Not contacted
A83: 82 | B83: HIGH | C83: No own website | D83: Booval Seafood | E83: takeaway | F83: Ipswich | G83: Facebook | I83: https://www.facebook.com/boovalseafood/ | J83: +61 7 3812 2888 | K83: https://www.facebook.com/boovalseafood/ | L83: no real website (uses www.facebook.com) | M83: Hi Booval Seafood team! [one real detail from their page]. We're AceAds, a web design studio. We noticed that when people in Ipswich search for a takeaway on Google, they only find your Facebook, not a website of your own. We'd be happy to make you a free preview of what a website could look like. Want one? No cost, no obligation. | N83: Open map | O83: Not contacted
A84: 83 | B84: HIGH | C84: No own website | D84: The Grazing Goat Cafe | E84: cafe | F84: Mackay | G84: Facebook | I84: https://www.facebook.com/GrazingGoatCafe/ | J84: +61 7 4953 2623 | K84: https://www.facebook.com/GrazingGoatCafe/ | L84: no real website (uses www.facebook.com) | M84: Hi The Grazing Goat Cafe team! [one real detail from their page]. We're AceAds, a web design studio. We noticed that when people in Mackay search for a cafe on Google, they only find your Facebook, not a website of your own. We'd be happy to make you a free preview of what a website could look like. Want one? No cost, no obligation. | N84: Open map | O84: Not contacted
A85: 84 | B85: HIGH | C85: No own website | D85: RARE Bar & Grill | E85: restaurant | F85: Mackay | G85: Facebook | I85: https://www.facebook.com/rarebarandgrillmackay | J85: +61 437 176 863 | K85: https://www.facebook.com/rarebarandgrillmackay | L85: no real website (uses www.facebook.com) | M85: Hi RARE Bar & Grill team! [one real detail from their page]. We're AceAds, a web design studio. We noticed that when people in Mackay search for a restaurant on Google, they only find your Facebook, not a website of your own. We'd be happy to make you a free preview of what a website could look like. Want one? No cost, no obligation. | N85: Open map | O85: Not contacted
A86: 85 | B86: HIGH | C86: No own website | D86: U Rok Hair & Beauty | E86: barber or hairdresser | F86: Rockhampton | G86: Facebook | I86: https://www.facebook.com/URokHairMakeupDesign/ | J86: +61 419 727 326 | K86: https://www.facebook.com/URokHairMakeupDesign/ | L86: no real website (uses www.facebook.com) | M86: Hi U Rok Hair & Beauty team! [one real detail from their page]. We're AceAds, a web design studio. We noticed that when people in Rockhampton search for a hairdresser on Google, they only find your Facebook, not a website of your own. We'd be happy to make you a free preview of what a website could look like. Want one? No cost, no obligation. | N86: Open map | O86: Not contacted
A87: 86 | B87: HIGH | C87: No own website | D87: Coffee Society | E87: cafe | F87: Rockhampton | G87: Facebook | I87: https://www.facebook.com/coffeesocietyrockhampton/ | J87: +61 408 335 908 | K87: https://www.facebook.com/coffeesocietyrockhampton/ | L87: no real website (uses www.facebook.com) | M87: Hi Coffee Society team! [one real detail from their page]. We're AceAds, a web design studio. We noticed that when people in Rockhampton search for a cafe on Google, they only find your Facebook, not a website of your own. We'd be happy to make you a free preview of what a website could look like. Want one? No cost, no obligation. | N87: Open map | O87: Not contacted
A88: 87 | B88: HIGH | C88: No own website | D88: Rockhampton Fitness Centre | E88: gym or studio | F88: Rockhampton | G88: Facebook | I88: https://www.facebook.com/rockhamptonfitness.centre/ | J88: +61 7 4927 8880 | K88: https://www.facebook.com/rockhamptonfitness.centre/ | L88: no real website (uses www.facebook.com) | M88: Hi Rockhampton Fitness Centre team! [one real detail from their page]. We're AceAds, a web design studio. We noticed that when people in Rockhampton search for a gym on Google, they only find your Facebook, not a website of your own. We'd be happy to make you a free preview of what a website could look like. Want one? No cost, no obligation. | N88: Open map | O88: Not contacted
A89: 88 | B89: HIGH | C89: No own website | D89: Capricornia Remedial Massage | E89: massage or spa | F89: Rockhampton | G89: Facebook | I89: https://www.facebook.com/capricorniaremedialmassage | J89: +61 409 708 830 | K89: https://capricorniaremedialmassagerockhampton.gettimely.com/ | L89: no real website (uses capricorniaremedialmassagerockhampton.gettimely.com) | M89: Hi Capricornia Remedial Massage team! [one real detail from their page]. We're AceAds, a web design studio. We noticed that when people in Rockhampton search for a massage on Google, they only find your Facebook, not a website of your own. We'd be happy to make you a free preview of what a website could look like. Want one? No cost, no obligation. | N89: Open map | O89: Not contacted
A90: 89 | B90: HIGH | C90: No own website | D90: Parklands Bakery | E90: bakery | F90: Sunshine Coast | G90: Facebook | I90: https://facebook.com/parklandsbakery/ | J90: +61 7 5438 2211 | K90: https://facebook.com/parklandsbakery/ | L90: no real website (uses facebook.com) | M90: Hi Parklands Bakery team! [one real detail from their page]. We're AceAds, a web design studio. We noticed that when people in Sunshine Coast search for a bakery on Google, they only find your Facebook, not a website of your own. We'd be happy to make you a free preview of what a website could look like. Want one? No cost, no obligation. | N90: Open map | O90: Not contacted
A91: 90 | B91: HIGH | C91: No own website | D91: Pete's Village Bakery | E91: bakery | F91: Sunshine Coast | G91: Facebook | I91: https://www.facebook.com/petesvillagebakery | J91: +61 7 5446 7629 | K91: https://www.facebook.com/petesvillagebakery | L91: no real website (uses www.facebook.com) | M91: Hi Pete's Village Bakery team! [one real detail from their page]. We're AceAds, a web design studio. We noticed that when people in Sunshine Coast search for a bakery on Google, they only find your Facebook, not a website of your own. We'd be happy to make you a free preview of what a website could look like. Want one? No cost, no obligation. | N91: Open map | O91: Not contacted
A92: 91 | B92: HIGH | C92: No own website | D92: Hair at Mooloolaba | E92: barber or hairdresser | F92: Sunshine Coast | G92: Facebook | I92: https://m.facebook.com/@hairstudiomooloolabah | J92: +61 7 5294 6373 | K92: https://m.facebook.com/@hairstudiomooloolabah | L92: no real website (uses m.facebook.com) | M92: Hi Hair at Mooloolaba team! [one real detail from their page]. We're AceAds, a web design studio. We noticed that when people in Sunshine Coast search for a hairdresser on Google, they only find your Facebook, not a website of your own. We'd be happy to make you a free preview of what a website could look like. Want one? No cost, no obligation. | N92: Open map | O92: Not contacted
A93: 92 | B93: HIGH | C93: No own website | D93: Ocean Spa Nails | E93: beauty salon | F93: Sunshine Coast | G93: Facebook | I93: https://www.facebook.com/Ocean-Spa-Nails-Currimundi-100394445284468/ | J93: +61 7 5337 6337 | K93: https://www.facebook.com/Ocean-Spa-Nails-Currimundi-100394445284468/ | L93: no real website (uses www.facebook.com) | M93: Hi Ocean Spa Nails team! [one real detail from their page]. We're AceAds, a web design studio. We noticed that when people in Sunshine Coast search for a beauty salon on Google, they only find your Facebook, not a website of your own. We'd be happy to make you a free preview of what a website could look like. Want one? No cost, no obligation. | N93: Open map | O93: Not contacted
... A96: 95 | B96: HIGH | C96: No own website | D96: Clancy's Beachside Takeaway | E96: takeaway | F96: Sunshine Coast | G96: Facebook | I96: https://www.facebook.com/clancys.beachside.takeaway/ | J96: +61 7 5491 3940 | K96: https://www.facebook.com/clancys.beachside.takeaway/ | L96: no real website (uses www.facebook.com) | M96: Hi Clancy's Beachside Takeaway team! [one real detail from their page]. We're AceAds, a web design studio. We noticed that when people in Sunshine Coast search for a takeaway on Google, they only find your Facebook, not a website of your own. We'd be happy to make you a free preview of what a website could look like. Want one? No cost, no obligation. | N96: Open map | O96: Not contacted
A97: 96 | B97: HIGH | C97: No own website | D97: Australian Hotel | E97: bar or pub | F97: Townsville | G97: Facebook | I97: https://www.facebook.com/australianhoteltownsville | K97: https://www.facebook.com/australianhoteltownsville | L97: no real website (uses www.facebook.com) | M97: Hi Australian Hotel team! [one real detail from their page]. We're AceAds, a web design studio. We noticed that when people in Townsville search for a bar on Google, they only find your Facebook, not a website of your own. We'd be happy to make you a free preview of what a website could look like. Want one? No cost, no obligation. | N97: Open map | O97: Not contacted
A98: 97 | B98: HIGH | C98: No own website | D98: Gentleman Jones Barber Shop | E98: barber or hairdresser | F98: Townsville | G98: Facebook | I98: https://www.facebook.com/pages/category/Local-Business/Gentleman-Jones-235990806595718 | K98: https://www.facebook.com/pages/category/Local-Business/Gentleman-Jones-235990806595718 | L98: no real website (uses www.facebook.com) | M98: Hi Gentleman Jones Barber Shop team! [one real detail from their page]. We're AceAds, a web design studio. We noticed that when people in Townsville search for a hairdresser on Google, they only find your Facebook, not a website of your own. We'd be happy to make you a free preview of what a website could look like. Want one? No cost, no obligation. | N98: Open map | O98: Not contacted
A99: 98 | B99: HIGH | C99: No own website | D99: She Creative Hair | E99: barber or hairdresser | F99: Townsville | G99: Facebook | I99: https://www.facebook.com/shecreativehair.com.au/ | J99: +61 7 4721 1110 | K99: https://www.facebook.com/shecreativehair.com.au/ | L99: no real website (uses www.facebook.com) | M99: Hi She Creative Hair team! [one real detail from their page]. We're AceAds, a web design studio. We noticed that when people in Townsville search for a hairdresser on Google, they only find your Facebook, not a website of your own. We'd be happy to make you a free preview of what a website could look like. Want one? No cost, no obligation. | N99: Open map | O99: Not contacted
A100: 99 | B100: HIGH | C100: No own website | D100: Alt Brew | E100: cafe | F100: Townsville | G100: Facebook | I100: https://www.facebook.com/Alt-Brew-1325275994229457 | K100: https://www.facebook.com/Alt-Brew-1325275994229457 | L100: no real website (uses www.facebook.com) | M100: Hi Alt Brew team! [one real detail from their page]. We're AceAds, a web design studio. We noticed that when people in Townsville search for a cafe on Google, they only find your Facebook, not a website of your own. We'd be happy to make you a free preview of what a website could look like. Want one? No cost, no obligation. | N100: Open map | O100: Not contacted
A101: 100 | B101: HIGH | C101: No own website | D101: Old Railway Cafe | E101: cafe | F101: Townsville | G101: Facebook | I101: https://www.facebook.com/theoldrailwaycafe | K101: https://www.facebook.com/theoldrailwaycafe | L101: no real website (uses www.facebook.com) | M101: Hi Old Railway Cafe team! [one real detail from their page]. We're AceAds, a web design studio. We noticed that when people in Townsville search for a cafe on Google, they only find your Facebook, not a website of your own. We'd be happy to make you a free preview of what a website could look like. Want one? No cost, no obligation. | N101: Open map | O101: Not contacted
A102: 101 | B102: HIGH | C102: No own website | D102: The Spirited Goat | E102: cafe | F102: Townsville | G102: Facebook | I102: https://www.facebook.com/The-Spirited-Goat-475954869187116 | K102: https://www.facebook.com/The-Spirited-Goat-475954869187116 | L102: no real website (uses www.facebook.com) | M102: Hi The Spirited Goat team! [one real detail from their page]. We're AceAds, a web design studio. We noticed that when people in Townsville search for a cafe on Google, they only find your Facebook, not a website of your own. We'd be happy to make you a free preview of what a website could look like. Want one? No cost, no obligation. | N102: Open map | O102: Not contacted
...

Sheet Tracker
A1: Pipeline | B1: Leads
A2: Not contacted | B2: =COUNTIF(Leads!O:O,"Not contacted")
A3: DM sent | B3: =COUNTIF(Leads!O:O,"DM sent")
A4: Replied | B4: =COUNTIF(Leads!O:O,"Replied")
A5: Preview sent | B5: =COUNTIF(Leads!O:O,"Preview sent")
A6: Meeting booked | B6: =COUNTIF(Leads!O:O,"Meeting booked")
A7: Won | B7: =COUNTIF(Leads!O:O,"Won")
A8: Not interested | B8: =COUNTIF(Leads!O:O,"Not interested")
A9: Business closed | B9: =COUNTIF(Leads!O:O,"Business closed")
A11: Reply rate (Replied or later / DMs sent) | B11: =IFERROR((B4+B5+B6+B7+B8)/(B3+B4+B5+B6+B7+B8),0)
A12: Leads per priority
A13: HIGH | B13: =COUNTIF(Leads!B:B,"HIGH")
A14: VERIFY FIRST | B14: =COUNTIF(Leads!B:B,"VERIFY FIRST")
A15: MEDIUM | B15: =COUNTIF(Leads!B:B,"MEDIUM")
A17: Leads per region
A18: Airlie Beach | B18: =COUNTIF(Leads!F:F,"Airlie Beach")
A19: Brisbane | B19: =COUNTIF(Leads!F:F,"Brisbane")
A20: Bundaberg | B20: =COUNTIF(Leads!F:F,"Bundaberg")
A21: Cairns | B21: =COUNTIF(Leads!F:F,"Cairns")
A22: Gladstone | B22: =COUNTIF(Leads!F:F,"Gladstone")
A23: Gold Coast | B23: =COUNTIF(Leads!F:F,"Gold Coast")
A24: Gympie | B24: =COUNTIF(Leads!F:F,"Gympie")
A25: Hervey Bay | B25: =COUNTIF(Leads!F:F,"Hervey Bay")
A26: Ipswich | B26: =COUNTIF(Leads!F:F,"Ipswich")
A27: Mackay | B27: =COUNTIF(Leads!F:F,"Mackay")
A28: Maryborough | B28: =COUNTIF(Leads!F:F,"Maryborough")
A29: Moreton Bay | B29: =COUNTIF(Leads!F:F,"Moreton Bay")
A30: Redlands | B30: =COUNTIF(Leads!F:F,"Redlands")
A31: Rockhampton | B31: =COUNTIF(Leads!F:F,"Rockhampton")
A32: Sunshine Coast | B32: =COUNTIF(Leads!F:F,"Sunshine Coast")
A33: Toowoomba | B33: =COUNTIF(Leads!F:F,"Toowoomba")
A34: Townsville | B34: =COUNTIF(Leads!F:F,"Townsville")
A35: Warwick | B35: =COUNTIF(Leads!F:F,"Warwick")

Sheet How to work this list
A1: AceAds: Instagram / Facebook outreach, Queensland
A3: Before each DM
A4: 1. Open 'Check on Google Maps'. Skip the business if it is closed or has almost no reviews.
A5: 2. Open their Instagram/Facebook. Replace [one real detail from their page] with something true and specific.
A6: 3. 'VERIFY FIRST' rows: Google the business name first. If they DO have a website, check it on your phone and
A7: rewrite the DM around a problem you can see yourself, or skip them. Never say they have no website unless you checked.
A8: 4. 'Slow to load' was timed from an overseas server. Open the site on your own phone first; if it loads fine, skip that point.
A10: Sending
A11: 5. Send from the AceAds business account, by hand. Max 20 new DMs per account per day.
A12: 6. Never paste the identical message twice in a row. Personalise every one; Meta limits accounts that send copy-paste DMs.
A13: 7. If they reply yes, ask AceAds for their preview (mockups/ in the repo), then send the screenshot and link.
A14: Set Status to 'Preview sent'.
... A24: Source: OpenStreetMap (c) OpenStreetMap contributors, plus links found on the businesses' own websites.
